exasol/saas/client/__init__.py
exasol/saas/client/openapi/__init__.py
exasol/saas/client/openapi/api/__init__.py
exasol/saas/client/openapi/api/clusters/__init__.py
exasol/saas/client/openapi/api/clusters/create_cluster.py
exasol/saas/client/openapi/api/clusters/delete_cluster.py
exasol/saas/client/openapi/api/clusters/get_cluster.py
exasol/saas/client/openapi/api/clusters/get_cluster_connection.py
exasol/saas/client/openapi/api/clusters/list_clusters.py
exasol/saas/client/openapi/api/clusters/scale_cluster.py
exasol/saas/client/openapi/api/clusters/start_cluster.py
exasol/saas/client/openapi/api/clusters/stop_cluster.py
exasol/saas/client/openapi/api/clusters/update_cluster.py
exasol/saas/client/openapi/api/databases/__init__.py
exasol/saas/client/openapi/api/databases/create_database.py
exasol/saas/client/openapi/api/databases/delete_database.py
exasol/saas/client/openapi/api/databases/get_database.py
exasol/saas/client/openapi/api/databases/list_databases.py
exasol/saas/client/openapi/api/databases/start_database.py
exasol/saas/client/openapi/api/databases/stop_database.py
exasol/saas/client/openapi/api/databases/update_database.py
exasol/saas/client/openapi/api/extensions/__init__.py
exasol/saas/client/openapi/api/extensions/create_extension_instance.py
exasol/saas/client/openapi/api/extensions/delete_extension_instance.py
exasol/saas/client/openapi/api/extensions/get_extension.py
exasol/saas/client/openapi/api/extensions/install_extension.py
exasol/saas/client/openapi/api/extensions/list_extension_instances.py
exasol/saas/client/openapi/api/extensions/list_extensions.py
exasol/saas/client/openapi/api/extensions/uninstall_extension.py
exasol/saas/client/openapi/api/files/__init__.py
exasol/saas/client/openapi/api/files/create_folder.py
exasol/saas/client/openapi/api/files/delete_file.py
exasol/saas/client/openapi/api/files/delete_folder.py
exasol/saas/client/openapi/api/files/download_file.py
exasol/saas/client/openapi/api/files/list_files.py
saas_api-0.2.0.dist-info/entry_points.txt
saas_api-0.2.0.dist-info/LICENSE
saas_api-0.2.0.dist-info/WHEEL
saas_api-0.2.0.dist-info/METADATA
saas_api-0.2.0.dist-info/RECORD
